{"personId":13477,"webUrl":"https://www.kinopoisk.ru/name/13477/","nameRu":"Салли Филд","nameEn":"Sally Field","sex":"FEMALE","posterUrl":"https://kinopoiskapiunofficial.tech/images/actor_posters/kp/13477.jpg","growth":157,"birthday":"1946-11-06","death":null,"age":77,"birthplace":"Пасадена, Калифорния, США","deathplace":null,"spouses":[{"personId":32795,"name":"Алан Грейсман","divorced":true,"divorcedReason":"(развод)","sex":"MALE","children":1,"webUrl":"https://www.kinopoisk.ru/name/32795/","relation":"супруг"},{"personId":1483691,"name":"Стивен Крейг","divorced":true,"divorcedReason":"(развод)","sex":"UNKNOWN","children":2,"webUrl":"","relation":"супруг"}],"hasAwards":1,"profession":"Актриса, Продюсер, Режиссер","facts":["Полное имя - Салли Маргарет Филд (Sally Margaret Field).","У Салли Филд есть три сына: два сына от первого брака со Стивеном Крейгом - Питер Крейг (10.11.69) и Элайджа М. Крейг (25.05.72) и один сын от второго брака с Аланом Грейсманом - Сэмюэль Грейсман (02.12.87)."],"films":[{"filmId":881,"nameRu":"Там, где сердце","nameEn":"Where the Heart Is","rating":"7.6","general":false,"description":"Mama Lil","professionKey":"ACTOR"},{"filmId":448,"nameRu":"Форрест Гамп","nameEn":"Forrest Gump","rating":"8.9","general":true,"description":"Mrs. Gump","professionKey":"ACTOR"},{"filmId":1109,"nameRu":"Умереть молодым","nameEn":"Dying Young","rating":"7.7","general":true,"description":"","professionKey":"PRODUCER"},{"filmId":1911,"nameRu":"Век кино","nameEn":"A Century of Cinema","rating":"5.6","general":false,"description":"играет саму себя","professionKey":"HERSELF"},{"filmId":2558,"nameRu":"Стальные магнолии","nameEn":"Steel Magnolias","rating":"7.5","general":true,"description":"M'Lynn Eatenton","professionKey":"ACTOR"},{"filmId":2626,"nameRu":"Норма Рэй","nameEn":"Norma Rae","rating":"6.9","general":false,"description":"Norma Rae","professionKey":"ACTOR"},{"filmId":2809,"nameRu":"Проселочные дороги","nameEn":"Back Roads","rating":"6.2","general":false,"description":"Amy Post","professionKey":"ACTOR"},{"filmId":4026,"nameRu":"Герои","nameEn":"Heroes","rating":"5.4","general":false,"description":"Carol Bell","professionKey":"ACTOR"},{"filmId":4094,"nameRu":"Смоки и Бандит 2","nameEn":"Smokey and the Bandit II","rating":"6.8","general":false,"description":"Carrie","professionKey":"ACTOR"},{"filmId":4442,"nameRu":"Скажи, что это не так","nameEn":"Say It Isn't So","rating":"6.0","general":false,"description":"Valdine Wingfield","professionKey":"ACTOR"},{"filmId":4564,"nameRu":"Око за око","nameEn":"Eye for an Eye","rating":"6.2","general":false,"description":"Karen McCann","professionKey":"ACTOR"},{"filmId":5320,"nameRu":"Блондинка в законе 2","nameEn":"Legally Blonde 2: Red, White & Blonde","rating":"5.8","general":false,"description":"Congresswoman Rudd","professionKey":"ACTOR"},{"filmId":5939,"nameRu":"Миссис Даутфайр","nameEn":"Mrs. Doubtfire","rating":"7.7","general":true,"description":"Miranda Hillard","professionKey":"ACTOR"},{"filmId":6306,"nameRu":"Оставайся голодным","nameEn":"Stay Hungry","rating":"6.1","general":false,"description":"Mary Tate Farnsworth","professionKey":"ACTOR"},{"filmId":6560,"nameRu":"Мыльная пена","nameEn":"Soapdish","rating":"6.9","general":false,"description":"Celeste Talbert","professionKey":"ACTOR"},{"filmId":6879,"nameRu":"Изюминка","nameEn":"Punchline","rating":"6.7","general":false,"description":"Lilah Krytsick","professionKey":"ACTOR"},{"filmId":6879,"nameRu":"Изюминка","nameEn":"Punchline","rating":"6.7","general":false,"description":"в титрах не указана","professionKey":"PRODUCER"},{"filmId":6879,"nameRu":"Изюминка","nameEn":"Punchline","rating":"6.7","general":false,"description":"продюсер, в титрах не указана","professionKey":"PRODUCER"},{"filmId":7085,"nameRu":"Красивая","nameEn":"Beautiful","rating":null,"general":false,"description":"","professionKey":"DIRECTOR"},{"filmId":7235,"nameRu":"Поцелуй меня на прощанье","nameEn":"Kiss Me Goodbye","rating":"6.2","general":false,"description":"Kay","professionKey":"ACTOR"},{"filmId":8140,"nameRu":"Смоки и Бандит","nameEn":"Smokey and the Bandit","rating":"7.6","general":true,"description":"Carrie","professionKey":"ACTOR"},{"filmId":8944,"nameRu":"Дорога домой 2: Затерянные в Сан-Франциско","nameEn":"Homeward Bound II: Lost in San Francisco","rating":"7.6","general":false,"description":"Sassy, озвучка","professionKey":"ACTOR"},{"filmId":9285,"nameRu":"Только не без моей дочери","nameEn":"Not Without My Daughter","rating":"7.4","general":false,"description":"Betty Mahmoody","professionKey":"ACTOR"},{"filmId":9863,"nameRu":"Потерянные дети Берлина","nameEn":"The Lost Children of Berlin","rating":null,"general":false,"description":"исполнительный продюсер","professionKey":"PRODUCER"},{"filmId":11885,"nameRu":"Идти на уступки","nameEn":"Surrender","rating":"6.1","general":false,"description":"Daisy Morgan","professionKey":"ACTOR"},{"filmId":11890,"nameRu":"Пленники Посейдона","nameEn":"Beyond the Poseidon Adventure","rating":"5.6","general":false,"description":"Celeste Whitman","professionKey":"ACTOR"},{"filmId":11929,"nameRu":"Путь на Запад","nameEn":"The Way West","rating":"6.6","general":false,"description":"Mercy McBee","professionKey":"ACTOR"},{"filmId":13958,"nameRu":"Без злого умысла","nameEn":"Absence of Malice","rating":"6.8","general":false,"description":"Megan","professionKey":"ACTOR"},{"filmId":14471,"nameRu":"Любовь Мерфи","nameEn":"Murphy's Romance","rating":"6.8","general":false,"description":"Emma Moriarity","professionKey":"ACTOR"},{"filmId":14471,"nameRu":"Любовь Мерфи","nameEn":"Murphy's Romance","rating":"6.8","general":false,"description":"Emma Moriarty","professionKey":"ACTOR"},{"filmId":15389,"nameRu":"Конец","nameEn":"The End","rating":"5.7","general":false,"description":"Mary Ellen","professionKey":"ACTOR"},{"filmId":15933,"nameRu":"Дорога домой: Невероятное путешествие","nameEn":"Homeward Bound: The Incredible Journey","rating":"7.9","general":false,"description":"Sassy, озвучка","professionKey":"ACTOR"},{"filmId":15934,"nameRu":"Место в сердце","nameEn":"Places in the Heart","rating":"7.3","general":false,"description":"Edna Spalding","professionKey":"ACTOR"},{"filmId":15935,"nameRu":"Хупер","nameEn":"Hooper","rating":"6.4","general":false,"description":"Gwen","professionKey":"ACTOR"},{"filmId":15935,"nameRu":"Хупер","nameEn":"Hooper","rating":"6.4","general":false,"description":"Gwen Doyle","professionKey":"ACTOR"},{"filmId":16324,"nameRu":"Лунный пилот","nameEn":"Moon Pilot","rating":null,"general":false,"description":"","professionKey":"HRONO_TITR_FEMALE"},{"filmId":60684,"nameRu":"100 лет кино","nameEn":"100 Years at the Movies","rating":"6.4","general":false,"description":"играет саму себя, хроника","professionKey":"HERSELF"},{"filmId":79741,"nameRu":"Скорая помощь","nameEn":"ER","rating":"8.2","general":false,"description":"Maggie Wyczenski","professionKey":"ACTOR"},{"filmId":81222,"nameRu":"Дэвид Копперфилд","nameEn":"David Copperfield","rating":"7.3","general":false,"description":"Aunt Betsey Trotwood","professionKey":"ACTOR"},{"filmId":93403,"nameRu":null,"nameEn":"Going Through Splat: The Life and Work of Stewart Stern","rating":null,"general":false,"description":"играет саму себя","professionKey":"HERSELF"},{"filmId":102122,"nameRu":"Линкольн","nameEn":"Lincoln","rating":"6.9","general":false,"description":"Mary Todd Lincoln","professionKey":"ACTOR"},{"filmId":102244,"nameRu":"Две недели","nameEn":"Two Weeks","rating":"6.5","general":false,"description":"Anita Bergman","professionKey":"ACTOR"},{"filmId":102751,"nameRu":"Служанка","nameEn":"A Cooler Climate","rating":null,"general":false,"description":"Iris","professionKey":"ACTOR"},{"filmId":251704,"nameRu":"Истории фестиваля","nameEn":"Histoires de festival","rating":null,"general":false,"description":"играет саму себя, хроника","professionKey":"HERSELF"},{"filmId":261153,"nameRu":"Испытание артистов","nameEn":"Épreuves d'artistes","rating":"3.3","general":false,"description":"играет саму себя, хроника","professionKey":"HERSELF"},{"filmId":277623,"nameRu":"С Земли на Луну","nameEn":"From the Earth to the Moon","rating":"7.0","general":false,"description":"","professionKey":"DIRECTOR"},{"filmId":277623,"nameRu":"С Земли на Луну","nameEn":"From the Earth to the Moon","rating":"7.0","general":false,"description":"Trudy Cooper","professionKey":"ACTOR"},{"filmId":277656,"nameRu":"Мерфи Браун","nameEn":"Murphy Brown","rating":"5.5","general":false,"description":"Secretary #91, Kathleen Dubek","professionKey":"ACTOR"},{"filmId":277858,"nameRu":"Диснейленд","nameEn":"Disneyland","rating":"7.9","general":false,"description":"играет саму себя","professionKey":"HERSELF"},{"filmId":277949,"nameRu":"Хохмы Роуэна и Мартина","nameEn":"Laugh-In","rating":"5.4","general":false,"description":"Various Roles","professionKey":"ACTOR"},{"filmId":277968,"nameRu":"Доктор Маркус Уэлби","nameEn":"Marcus Welby, M.D.","rating":"5.2","general":false,"description":"Jan Wilkins","professionKey":"ACTOR"},{"filmId":277977,"nameRu":"Мир Брэкена","nameEn":"Bracken's World","rating":null,"general":false,"description":"Jenny Marsh","professionKey":"ACTOR"},{"filmId":278060,"nameRu":"Сибил","nameEn":"Sybil","rating":"8.2","general":false,"description":"Sybil","professionKey":"ACTOR"},{"filmId":278217,"nameRu":"Новый Человек-паук","nameEn":"The Amazing Spider-Man","rating":"6.9","general":false,"description":"Aunt May","professionKey":"ACTOR"},{"filmId":281026,"nameRu":null,"nameEn":"The Man Who Shot Chinatown: The Life and Work of John A. Alonzo","rating":null,"general":false,"description":"играет саму себя","professionKey":"HERSELF"},{"filmId":295926,"nameRu":"Ночная галерея","nameEn":"Night Gallery","rating":"6.4","general":false,"description":"Irene Evans","professionKey":"ACTOR"},{"filmId":296335,"nameRu":"С Рождеством, Джордж Бейли","nameEn":"Merry Christmas, George Bailey","rating":null,"general":false,"description":"Mrs. Bailey / рассказчик","professionKey":"ACTOR"},{"filmId":296513,"nameRu":null,"nameEn":"All the Way Home","rating":null,"general":false,"description":"Mary Follet","professionKey":"ACTOR"},{"filmId":296514,"nameRu":"Брак: Первый год","nameEn":"Marriage: Year One","rating":null,"general":false,"description":"Jane Duden","professionKey":"ACTOR"},{"filmId":296515,"nameRu":"Возможно я вернусь домой весной","nameEn":"Maybe I'll Come Home in the Spring","rating":null,"general":false,"description":"Denise «Dennie» Miller","professionKey":"ACTOR"},{"filmId":296516,"nameRu":"Субботним вечером в прямом эфире: Рождество","nameEn":"Saturday Night Live Christmas","rating":null,"general":false,"description":"","professionKey":"HRONO_TITR_FEMALE"},{"filmId":298470,"nameRu":"Прозвища Смит и Джонс","nameEn":"Alias Smith and Jones","rating":null,"general":false,"description":"Clementine Hale","professionKey":"ACTOR"},{"filmId":301809,"nameRu":"За кадром: Пленники Посейдона","nameEn":"Behind the Scenes: Beyond the Poseidon Adventure","rating":null,"general":false,"description":"играет саму себя","professionKey":"HERSELF"},{"filmId":305853,"nameRu":"Убежденность","nameEn":"Conviction","rating":null,"general":false,"description":"","professionKey":"ACTOR"},{"filmId":308804,"nameRu":"Русалочка: Начало истории Ариэль","nameEn":"The Little Mermaid: Ariel's Beginning","rating":"7.2","general":false,"description":"Marina Del Ray, озвучка","professionKey":"ACTOR"},{"filmId":326535,"nameRu":"Монго опять в городе","nameEn":"Mongo's Back in Town","rating":null,"general":false,"description":"Vikki","professionKey":"ACTOR"},{"filmId":327250,"nameRu":null,"nameEn":"Lily for President?","rating":null,"general":false,"description":"Beth Barber","professionKey":"ACTOR"},{"filmId":327459,"nameRu":null,"nameEn":"Bridger","rating":null,"general":false,"description":"Jennifer Melford","professionKey":"ACTOR"},{"filmId":327460,"nameRu":"После венца","nameEn":"Hitched","rating":null,"general":false,"description":"Roselle Bridgeman","professionKey":"ACTOR"},{"filmId":327461,"nameRu":"Домой на праздники","nameEn":"Home for the Holidays","rating":null,"general":false,"description":"Christine Morgan","professionKey":"ACTOR"},{"filmId":327462,"nameRu":"Рождественская ель","nameEn":"The Christmas Tree","rating":null,"general":false,"description":"","professionKey":"DIRECTOR"},{"filmId":327462,"nameRu":"Рождественская ель","nameEn":"The Christmas Tree","rating":null,"general":false,"description":"исполнительный продюсер","professionKey":"PRODUCER"},{"filmId":327462,"nameRu":"Рождественская ель","nameEn":"The Christmas Tree","rating":null,"general":false,"description":"телепьеса","professionKey":"WRITER"},{"filmId":329480,"nameRu":"Гиджет","nameEn":"Gidget","rating":null,"general":false,"description":"Frances Elizabeth «Gidget» Lawrence","professionKey":"ACTOR"},{"filmId":393877,"nameRu":"Биография","nameEn":"Biography","rating":"7.9","general":false,"description":"играет саму себя","professionKey":"HERSELF"},{"filmId":395374,"nameRu":"Царь горы","nameEn":"King of the Hill","rating":"6.9","general":false,"description":"Junie Harper","professionKey":"ACTOR"},{"filmId":397353,"nameRu":"Шоу Грэма Нортона","nameEn":"The Graham Norton Show","rating":"8.3","general":false,"description":"играет саму себя - гость","professionKey":"HERSELF"},{"filmId":400027,"nameRu":"Братья и сестры","nameEn":"Brothers & Sisters","rating":"7.8","general":false,"description":"Nora Walker","professionKey":"ACTOR"},{"filmId":400027,"nameRu":"Братья и сестры","nameEn":"Brothers & Sisters","rating":"7.8","general":false,"description":"исполнительный продюсер","professionKey":"PRODUCER"},{"filmId":400491,"nameRu":"Великие представления","nameEn":"Great Performances","rating":"6.3","general":false,"description":"играет саму себя","professionKey":"HERSELF"},{"filmId":400753,"nameRu":"Saturday Night Live","nameEn":"Saturday Night Live","rating":"8.3","general":false,"description":"Elizabeth Taylor","professionKey":"ACTOR"},{"filmId":400801,"nameRu":"Шоу Ларри Сандерса","nameEn":"The Larry Sanders Show","rating":"5.4","general":false,"description":"Sally Field","professionKey":"ACTOR"},{"filmId":401131,"nameRu":"В студии актерского мастерства","nameEn":"Inside the Actors Studio","rating":"8.4","general":false,"description":"играет саму себя - гость","professionKey":"HERSELF"},{"filmId":401146,"nameRu":null,"nameEn":"Carol Burnett & Company","rating":null,"general":false,"description":"играет саму себя","professionKey":"HERSELF"},{"filmId":401592,"nameRu":"Америка: Дань героям","nameEn":"America: A Tribute to Heroes","rating":"5.4","general":false,"description":"играет саму себя","professionKey":"HERSELF"},{"filmId":404000,"nameRu":"Американский институт киноискусства: 100 лет... 100 героев и злодеев","nameEn":"AFI's 100 Years... 100 Heroes & Villains","rating":"6.3","general":false,"description":"играет саму себя","professionKey":"HERSELF"},{"filmId":404002,"nameRu":"Режиссеры","nameEn":"The Directors","rating":"6.8","general":false,"description":"играет саму себя","professionKey":"HERSELF"},{"filmId":404942,"nameRu":"Взгляд","nameEn":"The View","rating":"6.2","general":false,"description":"играет саму себя - гость","professionKey":"HERSELF"},{"filmId":405526,"nameRu":"Шоу Рози О`Доннелл","nameEn":"The Rosie O'Donnell Show","rating":"6.1","general":false,"description":"играет саму себя - гость","professionKey":"HERSELF"},{"filmId":407338,"nameRu":"Джимми Киммел в прямом эфире","nameEn":"Jimmy Kimmel Live!","rating":"7.6","general":false,"description":"играет саму себя - гость","professionKey":"HERSELF"},{"filmId":408362,"nameRu":"Ночное шоу с Джейем Лено","nameEn":"The Tonight Show with Jay Leno","rating":"7.2","general":false,"description":"играет саму себя - гость","professionKey":"HERSELF"},{"filmId":408980,"nameRu":"Переосмысление Голливуда","nameEn":"Reinventando Hollywood","rating":"6.5","general":false,"description":"играет саму себя / Nora Walker, хроника","professionKey":"HERSELF"},{"filmId":445223,"nameRu":"Вечернее шоу Джонни Карсона","nameEn":"The Tonight Show Starring Johnny Carson","rating":"5.6","general":false,"description":"играет саму себя - гость","professionKey":"HERSELF"},{"filmId":445244,"nameRu":"Шоу Тони Данца","nameEn":"The Tony Danza Show","rating":"5.3","general":false,"description":"играет саму себя - гость","professionKey":"HERSELF"},{"filmId":445866,"nameRu":"Эллен: Шоу Эллен ДеДженерес","nameEn":"Ellen: The Ellen DeGeneres Show","rating":"8.1","general":false,"description":"играет саму себя - гость","professionKey":"HERSELF"},{"filmId":445888,"nameRu":"Воган","nameEn":"Wogan","rating":"4.8","general":false,"description":"играет саму себя","professionKey":"HERSELF"},{"filmId":445888,"nameRu":"Воган","nameEn":"Wogan","rating":"4.8","general":false,"description":"играет саму себя - гость","professionKey":"HERSELF"},{"filmId":445894,"nameRu":"Выстоим против рака","nameEn":"Stand Up to Cancer","rating":"7.6","general":false,"description":"играет саму себя","professionKey":"HERSELF"},{"filmId":455419,"nameRu":null,"nameEn":"Barbara Stanwyck: Fire and Desire","rating":null,"general":false,"description":"играет саму себя - ведущая","professionKey":"HERSELF"},{"filmId":469190,"nameRu":"В прямом эфире с Риджесом и Кэти Ли","nameEn":"Live with Regis and Kathie Lee","rating":"7.2","general":false,"description":"играет саму себя - гость","professionKey":"HERSELF"},{"filmId":485983,"nameRu":"Пустыня запрещенного искусства","nameEn":"The Desert of Forbidden Art","rating":null,"general":false,"description":"озвучка","professionKey":"ACTOR"},{"filmId":494422,"nameRu":"Шоу Мерва Гриффина","nameEn":"The Merv Griffin Show","rating":"4.7","general":false,"description":"играет саму себя","professionKey":"HERSELF"},{"filmId":496688,"nameRu":"67-я церемония вручения премии «Оскар»","nameEn":"The 67th Annual Academy Awards","rating":"6.0","general":false,"description":"играет саму себя - презентатор","professionKey":"HERSELF"},{"filmId":496691,"nameRu":"64-я церемония вручения премии «Оскар»","nameEn":"The 64th Annual Academy Awards","rating":"5.9","general":false,"description":"играет саму себя - презентатор: «Beauty and the beast» Clip","professionKey":"HERSELF"},{"filmId":496692,"nameRu":"63-я церемония вручения премии «Оскар»","nameEn":"The 63rd Annual Academy Awards","rating":"6.0","general":false,"description":"играет саму себя - Favorite Films Segment","professionKey":"HERSELF"},{"filmId":496697,"nameRu":"58-я церемония вручения премии «Оскар»","nameEn":"The 58th Annual Academy Awards","rating":"5.6","general":false,"description":"играет саму себя - презентатор","professionKey":"HERSELF"},{"filmId":496698,"nameRu":"57-я церемония вручения премии «Оскар»","nameEn":"The 57th Annual Academy Awards","rating":"5.3","general":false,"description":"играет саму себя - Winner","professionKey":"HERSELF"},{"filmId":496698,"nameRu":"57-я церемония вручения премии «Оскар»","nameEn":"The 57th Annual Academy Awards","rating":"5.3","general":false,"description":"играет саму себя - Winner: Best Actress in a Leading Role","professionKey":"HERSELF"},{"filmId":496702,"nameRu":"53-я церемония вручения премии «Оскар»","nameEn":"53rd Annual Academy Awards","rating":"5.0","general":false,"description":"играет саму себя - презентатор","professionKey":"HERSELF"},{"filmId":496702,"nameRu":"53-я церемония вручения премии «Оскар»","nameEn":"53rd Annual Academy Awards","rating":"5.0","general":false,"description":"играет саму себя - презентатор: Best Actor in a Leading Role","professionKey":"HERSELF"},{"filmId":496703,"nameRu":"52-я церемония вручения премии «Оскар»","nameEn":"52nd Annual Academy Awards","rating":"5.1","general":false,"description":"играет саму себя - Winner","professionKey":"HERSELF"},{"filmId":496703,"nameRu":"52-я церемония вручения премии «Оскар»","nameEn":"52nd Annual Academy Awards","rating":"5.1","general":false,"description":"играет саму себя - Winner: Best Actress in a Leading Role","professionKey":"HERSELF"},{"filmId":505972,"nameRu":null,"nameEn":"Accidental Icon: The Real Gidget Story","rating":null,"general":false,"description":"играет саму себя","professionKey":"HERSELF"},{"filmId":542227,"nameRu":"Независимая линза","nameEn":"Independent Lens","rating":"5.6","general":false,"description":"","professionKey":"ACTOR"},{"filmId":542231,"nameRu":"Между двумя папоротниками с Заком Галифианакисом","nameEn":"Between Two Ferns with Zach Galifianakis","rating":"7.8","general":false,"description":"играет саму себя","professionKey":"HERSELF"},{"filmId":542597,"nameRu":"47-я церемония вручения премии «Золотой глобус»","nameEn":"The 47th Annual Golden Globe Awards 1990","rating":"4.8","general":false,"description":"играет саму себя - номинантка","professionKey":"HERSELF"},{"filmId":542597,"nameRu":"47-я церемония вручения премии «Золотой глобус»","nameEn":"The 47th Annual Golden Globe Awards 1990","rating":"4.8","general":false,"description":"играет саму себя - номинантка: Best Actress in a Motion Picture - Drama","professionKey":"HERSELF"},{"filmId":543976,"nameRu":"6-я церемония вручения премии Гильдии киноактеров","nameEn":"6th Annual Screen Actors Guild Awards","rating":"5.5","general":false,"description":"играет саму себя - номинантка","professionKey":"HERSELF"},{"filmId":543979,"nameRu":"53-я церемония вручения прайм-тайм премии «Эмми»","nameEn":"The 53rd Annual Primetime Emmy Awards","rating":"5.7","general":false,"description":"играет самого себя - презентатор / играет саму себя - презентатор / играет саму себя - презентатор / играет саму себя - презентатор","professionKey":"HERSELF"},{"filmId":543985,"nameRu":"Тэвис Смайли","nameEn":"Tavis Smiley","rating":"5.8","general":false,"description":"играет саму себя - гость","professionKey":"HERSELF"},{"filmId":569975,"nameRu":"Рэйчел Рэй","nameEn":"Rachael Ray","rating":"6.3","general":false,"description":"играет саму себя - гость","professionKey":"HERSELF"},{"filmId":576054,"nameRu":"53-я церемония вручения премии «Золотой глобус»","nameEn":"53rd Annual Golden Globe Awards","rating":"5.4","general":false,"description":"играет саму себя - номинантка","professionKey":"HERSELF"},{"filmId":576054,"nameRu":"53-я церемония вручения премии «Золотой глобус»","nameEn":"53rd Annual Golden Globe Awards","rating":"5.4","general":false,"description":"играет саму себя - номинантка: Best Actress in a Mini-Series or Motion Picture Made for TV","professionKey":"HERSELF"},{"filmId":576060,"nameRu":"42-я церемония вручения премии «Золотой глобус»","nameEn":"The 42nd Annual Golden Globe Awards 1985","rating":null,"general":false,"description":"играет саму себя - Winner","professionKey":"HERSELF"},{"filmId":576060,"nameRu":"42-я церемония вручения премии «Золотой глобус»","nameEn":"The 42nd Annual Golden Globe Awards 1985","rating":null,"general":false,"description":"играет саму себя - Winner: Best Actress in a Motion Picture Drama","professionKey":"HERSELF"},{"filmId":576063,"nameRu":"37-я церемония вручения премии «Золотой глобус»","nameEn":"The 37th Annual Golden Globe Awards","rating":null,"general":false,"description":"играет саму себя","professionKey":"HERSELF"},{"filmId":576063,"nameRu":"37-я церемония вручения премии «Золотой глобус»","nameEn":"The 37th Annual Golden Globe Awards","rating":null,"general":false,"description":"играет саму себя - презентатор & Winner","professionKey":"HERSELF"},{"filmId":576080,"nameRu":"66-я церемония вручения премии «Золотой глобус»","nameEn":"2009 Golden Globe Awards","rating":"7.0","general":false,"description":"играет саму себя - номинантка","professionKey":"HERSELF"},{"filmId":584126,"nameRu":"Музыкальный фестиваль Live Aid","nameEn":"Live Aid","rating":"8.8","general":false,"description":"играет саму себя","professionKey":"HERSELF"},{"filmId":587593,"nameRu":"Развлечения сегодня вечером","nameEn":"Entertainment Tonight","rating":"7.2","general":false,"description":"играет саму себя","professionKey":"HERSELF"},{"filmId":590313,"nameRu":"Вечер с Джимми Фэллоном","nameEn":"Late Night with Jimmy Fallon","rating":"7.7","general":false,"description":"играет саму себя - гость","professionKey":"HERSELF"},{"filmId":594789,"nameRu":"Доброе утро, Америка","nameEn":"Good Morning America","rating":"6.8","general":false,"description":"играет саму себя - гость","professionKey":"HERSELF"},{"filmId":602409,"nameRu":"Новый Человек-паук: Высокое напряжение","nameEn":"The Amazing Spider-Man 2","rating":"6.7","general":false,"description":"Aunt May","professionKey":"ACTOR"},{"filmId":639274,"nameRu":null,"nameEn":"Ciné regards","rating":null,"general":false,"description":"играет саму себя","professionKey":"HERSELF"},{"filmId":654447,"nameRu":null,"nameEn":"James Stewart: A Wonderful Life - Hosted by Johnny Carson","rating":null,"general":false,"description":"играет саму себя","professionKey":"HERSELF"},{"filmId":655737,"nameRu":"Вечернее шоу с Дэвидом Леттерманом","nameEn":"Late Show with David Letterman","rating":"7.5","general":false,"description":"играет саму себя - гость","professionKey":"HERSELF"},{"filmId":666732,"nameRu":"Сделано в Голливуде","nameEn":"Made in Hollywood","rating":"7.6","general":false,"description":"играет саму себя","professionKey":"HERSELF"},{"filmId":667205,"nameRu":"Сегодня","nameEn":"Today","rating":"6.9","general":false,"description":"играет саму себя - гость","professionKey":"HERSELF"},{"filmId":674770,"nameRu":"Профили телеканала Bravo","nameEn":"Bravo Profiles","rating":null,"general":false,"description":"играет саму себя","professionKey":"HERSELF"},{"filmId":678537,"nameRu":"Разговор","nameEn":"The Talk","rating":"5.6","general":false,"description":"играет саму себя - гость","professionKey":"HERSELF"},{"filmId":679727,"nameRu":"15-я церемония вручения премии Гильдии киноактеров","nameEn":"15th Annual Screen Actors Guild Awards","rating":"5.4","general":false,"description":"играет саму себя - Winner: Female Actor in a Drama Series","professionKey":"HERSELF"},{"filmId":682065,"nameRu":"Выстоим против рака","nameEn":"Stand Up to Cancer","rating":null,"general":false,"description":"играет саму себя","professionKey":"HERSELF"},{"filmId":682509,"nameRu":"61-я церемония вручения прайм-тайм премии «Эмми»","nameEn":"The 61st Primetime Emmy Awards","rating":"5.9","general":false,"description":"играет саму себя - номинантка","professionKey":"HERSELF"},{"filmId":686423,"nameRu":"Отчёт Колбера","nameEn":"The Colbert Report","rating":"6.6","general":false,"description":"играет саму себя - гость","professionKey":"HERSELF"},{"filmId":688990,"nameRu":"59-я ежегодная церемония вручения премии «Тони»","nameEn":"The 59th Annual Tony Awards","rating":null,"general":false,"description":"играет саму себя - презентатор","professionKey":"HERSELF"},{"filmId":706016,"nameRu":"Смотрите, что происходит: Прямой эфир","nameEn":"Watch What Happens Live with Andy Cohen","rating":"5.3","general":false,"description":"играет саму себя","professionKey":"HERSELF"},{"filmId":708649,"nameRu":"60-я церемония вручения прайм-тайм премии «Эмми»","nameEn":"The 60th Primetime Emmy Awards","rating":"5.4","general":false,"description":"играет саму себя - презентатор","professionKey":"HERSELF"},{"filmId":708649,"nameRu":"60-я церемония вручения прайм-тайм премии «Эмми»","nameEn":"The 60th Primetime Emmy Awards","rating":"5.4","general":false,"description":"играет саму себя - презентатор: Outstanding Miniseries","professionKey":"HERSELF"},{"filmId":710265,"nameRu":null,"nameEn":"Rite of Passage: The Amazing Spider-Man Reborn","rating":null,"general":false,"description":"играет саму себя","professionKey":"HERSELF"},{"filmId":713601,"nameRu":"За едой","nameEn":"The Chew","rating":null,"general":false,"description":"играет самого себя - гость / играет саму себя - гость","professionKey":"HERSELF"},{"filmId":713601,"nameRu":"За едой","nameEn":"The Chew","rating":null,"general":false,"description":"играет саму себя - гость","professionKey":"HERSELF"},{"filmId":719332,"nameRu":"5-я ежегодная церемония вручения премии People's Choice Awards","nameEn":"The 5th Annual People's Choice Awards","rating":null,"general":false,"description":"играет саму себя - презентатор","professionKey":"HERSELF"},{"filmId":719332,"nameRu":"5-я ежегодная церемония вручения премии People's Choice Awards","nameEn":"The 5th Annual People's Choice Awards","rating":null,"general":false,"description":"играет саму себя - презентатор: Favourite Female Musical Performer","professionKey":"HERSELF"},{"filmId":723498,"nameRu":null,"nameEn":"12th Annual Prism Awards","rating":null,"general":false,"description":"играет саму себя - Winner","professionKey":"HERSELF"},{"filmId":730894,"nameRu":"70-я церемония вручения премии «Золотой глобус»","nameEn":"70th Golden Globe Awards","rating":"7.0","general":false,"description":"играет саму себя - номинантка","professionKey":"HERSELF"},{"filmId":731788,"nameRu":"18-я ежегодная церемония вручения премии Critics' Choice Movie Awards","nameEn":"18th Annual Critics' Choice Movie Awards","rating":"4.9","general":false,"description":"играет саму себя","professionKey":"HERSELF"},{"filmId":734456,"nameRu":"19-я церемония вручения премии Гильдии киноактеров","nameEn":"19th Annual Screen Actors Guild Awards","rating":"5.7","general":false,"description":"играет саму себя - номинантка & Presenter","professionKey":"HERSELF"},{"filmId":739604,"nameRu":"Летающая монахиня","nameEn":"The Flying Nun","rating":null,"general":false,"description":"Sister Bertrille","professionKey":"ACTOR"},{"filmId":745450,"nameRu":"Хохмы Роуэна и Мартина: 35-ая годовщина","nameEn":"Rowan & Martin's Laugh-In: 25th Anniversary Reunion","rating":null,"general":false,"description":"играет саму себя, хроника","professionKey":"HERSELF"},{"filmId":754983,"nameRu":"Кэти","nameEn":"Katie","rating":"4.8","general":false,"description":"играет саму себя - гость","professionKey":"HERSELF"},{"filmId":756628,"nameRu":"Фильм '72","nameEn":"Film '72","rating":"6.3","general":false,"description":"играет саму себя","professionKey":"HERSELF"},{"filmId":762788,"nameRu":"Репутация","nameEn":"Reputations","rating":null,"general":false,"description":"играет саму себя","professionKey":"HERSELF"},{"filmId":762889,"nameRu":"Самые яркие моменты церемонии «Оскар» (1971-1991)","nameEn":"Oscar's Greatest Moments","rating":null,"general":false,"description":"играет саму себя, хроника","professionKey":"HERSELF"},{"filmId":762890,"nameRu":"50 лет смешных женщин","nameEn":"50 Years of Funny Females","rating":null,"general":false,"description":"играет саму себя, хроника","professionKey":"HERSELF"},{"filmId":763104,"nameRu":"Один голос","nameEn":"One Voice","rating":null,"general":false,"description":"играет саму себя - член аудитории, в титрах не указана","professionKey":"HERSELF"},{"filmId":765074,"nameRu":"Шоу-бизнес сегодня","nameEn":"Showbiz Today","rating":"4.8","general":false,"description":"играет саму себя","professionKey":"HERSELF"},{"filmId":765075,"nameRu":"Аспел и компания","nameEn":"Aspel & Company","rating":null,"general":false,"description":"играет саму себя","professionKey":"HERSELF"},{"filmId":765077,"nameRu":"Сегодня утром","nameEn":"CBS This Morning","rating":"4.8","general":false,"description":"играет саму себя","professionKey":"HERSELF"},{"filmId":765077,"nameRu":"Сегодня утром","nameEn":"CBS This Morning","rating":"4.8","general":false,"description":"играет саму себя - гость","professionKey":"HERSELF"},{"filmId":766355,"nameRu":"Маленькое зло","nameEn":"Little Evil","rating":"5.6","general":false,"description":"Miss Shaylock","professionKey":"ACTOR"},{"filmId":772993,"nameRu":"Двадцатый век Фокс: Годы блокбастеров","nameEn":"Twentieth Century Fox: The Blockbuster Years","rating":"5.3","general":false,"description":"Norma Rae, хроника","professionKey":"HERSELF"},{"filmId":774110,"nameRu":"Американский институт киноискусства: 100 лет... 100 поздравлений: Самые вдохновляющие фильмы Америки","nameEn":"AFI's 100 Years... 100 Cheers: America's Most Inspiring Movies","rating":null,"general":false,"description":"играет саму себя","professionKey":"HERSELF"},{"filmId":780198,"nameRu":"Джулия Робертс: Трибьют американской синематике","nameEn":"Julia Roberts: An American Cinematheque Tribute","rating":null,"general":false,"description":"играет саму себя","professionKey":"HERSELF"},{"filmId":780199,"nameRu":"Бегство","nameEn":"Getaway","rating":"5.3","general":false,"description":"играет саму себя","professionKey":"HERSELF"},{"filmId":780530,"nameRu":"20-я церемония вручения прайм-тайм премии «Эмми»","nameEn":"The 20th Annual Primetime Emmy Awards","rating":null,"general":false,"description":"Presenter","professionKey":"HERSELF"},{"filmId":780530,"nameRu":"20-я церемония вручения прайм-тайм премии «Эмми»","nameEn":"The 20th Annual Primetime Emmy Awards","rating":null,"general":false,"description":"играет саму себя - презентатор","professionKey":"HERSELF"},{"filmId":780552,"nameRu":"Голливудские квадраты","nameEn":"The Hollywood Squares (Daytime)","rating":null,"general":false,"description":"играет саму себя - участник","professionKey":"HERSELF"},{"filmId":782800,"nameRu":"47-я церемония вручения прайм-тайм премии «Эмми»","nameEn":"The 47th Annual Primetime Emmy Awards","rating":null,"general":false,"description":"играет саму себя - Nominated: Outstanding Lead Actress in a Miniseries or a Special","professionKey":"HERSELF"},{"filmId":782800,"nameRu":"47-я церемония вручения прайм-тайм премии «Эмми»","nameEn":"The 47th Annual Primetime Emmy Awards","rating":null,"general":false,"description":"играет саму себя - номинантка","professionKey":"HERSELF"},{"filmId":782908,"nameRu":"59-я церемония вручения прайм-тайм премии «Эмми»","nameEn":"The 59th Primetime Emmy Awards","rating":null,"general":false,"description":"играет саму себя - Winner & Presenter","professionKey":"HERSELF"},{"filmId":783191,"nameRu":"67-я ежегодная церемония вручения премии «Тони»","nameEn":"The 67th Annual Tony Awards","rating":"5.7","general":false,"description":"играет саму себя - презентатор","professionKey":"HERSELF"},{"filmId":783191,"nameRu":"67-я ежегодная церемония вручения премии «Тони»","nameEn":"The 67th Annual Tony Awards","rating":"5.7","general":false,"description":"играет саму себя - презентатор: Best Leading Actor in a Musical & Best Leading Actor in a Play","professionKey":"HERSELF"},{"filmId":783245,"nameRu":"Шоу Дика Каветта","nameEn":"The Dick Cavett Show","rating":null,"general":false,"description":"играет саму себя - актриса","professionKey":"HERSELF"},{"filmId":787593,"nameRu":"Развлекательное шоу «Тротуары»","nameEn":"Sidewalks Entertainment","rating":"5.6","general":false,"description":"играет саму себя - гость","professionKey":"HERSELF"},{"filmId":796065,"nameRu":null,"nameEn":"The 8th Annual People's Choice Awards","rating":null,"general":false,"description":"играет саму себя - Winner","professionKey":"HERSELF"},{"filmId":796065,"nameRu":null,"nameEn":"The 8th Annual People's Choice Awards","rating":null,"general":false,"description":"играет саму себя - Winner: Favourite Actress in Motion Picture","professionKey":"HERSELF"},{"filmId":797967,"nameRu":"7-я церемония вручения премии Гильдии киноактеров","nameEn":"7th Annual Screen Actors Guild Awards","rating":null,"general":false,"description":"играет саму себя - номинантка","professionKey":"HERSELF"},{"filmId":797967,"nameRu":"7-я церемония вручения премии Гильдии киноактеров","nameEn":"7th Annual Screen Actors Guild Awards","rating":null,"general":false,"description":"играет саму себя - номинантка: Outstanding Performance by a Female Actor in a Drama Series and Outstanding Performance by an Ensemble in a Drama Series","professionKey":"HERSELF"},{"filmId":798182,"nameRu":"Paramount Pictures празднует 90-летие: 90 звёзд за 90 лет","nameEn":"Gala Paramount Pictures Celebrates 90th Anniversary with 90 Stars for 90 Years","rating":null,"general":false,"description":"играет саму себя","professionKey":"HERSELF"},{"filmId":802704,"nameRu":"Американский институт кино чествует Лиллиан Гиш","nameEn":"The American Film Institute Salute to Lillian Gish","rating":null,"general":false,"description":"играет саму себя","professionKey":"HERSELF"},{"filmId":802709,"nameRu":"Американский институт кино чествует Джека Леммона","nameEn":"The American Film Institute Salute to Jack Lemmon","rating":null,"general":false,"description":"играет саму себя, в титрах не указана","professionKey":"HERSELF"},{"filmId":802719,"nameRu":"Американский институт кино чествует Кирка Дугласа","nameEn":"The American Film Institute Salute to Kirk Douglas","rating":null,"general":false,"description":"играет саму себя, в титрах не указана","professionKey":"HERSELF"},{"filmId":802720,"nameRu":"Американский институт кино чествует Билли Уайлдера","nameEn":"The American Film Institute Salute to Billy Wilder","rating":null,"general":false,"description":"играет саму себя","professionKey":"HERSELF"},{"filmId":817858,"nameRu":"86-я церемония вручения премии «Оскар»","nameEn":"The Oscars","rating":"6.8","general":false,"description":"играет саму себя - презентатор","professionKey":"HERSELF"},{"filmId":837100,"nameRu":"Поздней ночью с Сетом Майерсом","nameEn":"Late Night with Seth Meyers","rating":"6.0","general":false,"description":"играет саму себя - гость","professionKey":"HERSELF"},{"filmId":837999,"nameRu":null,"nameEn":"Supermensch: The Legend of Shep Gordon","rating":null,"general":false,"description":"играет саму себя, хроника","professionKey":"HERSELF"},{"filmId":841160,"nameRu":"Инсайдер","nameEn":"The Insider","rating":"5.7","general":false,"description":"играет саму себя","professionKey":"HERSELF"},{"filmId":845996,"nameRu":"Здравствуйте, меня зовут Дорис","nameEn":"Hello, My Name Is Doris","rating":"6.6","general":false,"description":"Doris","professionKey":"ACTOR"},{"filmId":891560,"nameRu":"Позднее шоу со Стивеном Колбером","nameEn":"The Late Show with Stephen Colbert","rating":"6.4","general":false,"description":"играет саму себя - гость","professionKey":"HERSELF"},{"filmId":891588,"nameRu":"Очень позднее шоу с Джеймсом Корденом","nameEn":"The Late Late Show with James Corden","rating":"7.1","general":false,"description":"играет саму себя","professionKey":"HERSELF"},{"filmId":972200,"nameRu":"Маньяк","nameEn":"Maniac","rating":"7.4","general":false,"description":"Dr. Greta Mantleray","professionKey":"ACTOR"},{"filmId":976625,"nameRu":"Шоу Майка Дугласа","nameEn":"The Mike Douglas Show","rating":null,"general":false,"description":"играет саму себя - гость","professionKey":"HERSELF"},{"filmId":976629,"nameRu":null,"nameEn":"The Joey Bishop Show","rating":null,"general":false,"description":"играет саму себя","professionKey":"HERSELF"},{"filmId":983088,"nameRu":"Шестидесятые","nameEn":"The Sixties","rating":"7.3","general":false,"description":"играет саму себя","professionKey":"HERSELF"},{"filmId":991653,"nameRu":"Эй, хозяин!","nameEn":"Hey, Landlord","rating":null,"general":false,"description":"Bonnie Banner","professionKey":"ACTOR"},{"filmId":1007871,"nameRu":"Челси","nameEn":"Chelsea","rating":null,"general":false,"description":"играет саму себя - гость","professionKey":"HERSELF"},{"filmId":1049102,"nameRu":"Спилберг","nameEn":"Spielberg","rating":"8.0","general":false,"description":"играет саму себя - Actor","professionKey":"HERSELF"},{"filmId":1049102,"nameRu":"Спилберг","nameEn":"Spielberg","rating":"8.0","general":false,"description":"играет саму себя - Segment «Lincoln»","professionKey":"HERSELF"},{"filmId":1111391,"nameRu":"Робин Уильямс: Загляни в мою душу","nameEn":"Robin Williams: Come Inside My Mind","rating":"8.0","general":false,"description":"играет саму себя, хроника, в титрах не указана","professionKey":"HERSELF"},{"filmId":1111763,"nameRu":null,"nameEn":"Finding Your Roots with Henry Louis Gates, Jr.","rating":null,"general":false,"description":"играет саму себя","professionKey":"HERSELF"},{"filmId":1112141,"nameRu":null,"nameEn":"Ok! TV","rating":null,"general":false,"description":"играет саму себя","professionKey":"HERSELF"},{"filmId":1177528,"nameRu":null,"nameEn":"The Girl with Something Extra","rating":null,"general":false,"description":"Sally Burton","professionKey":"ACTOR"},{"filmId":1189999,"nameRu":"Послания из другого мира","nameEn":"Dispatches from Elsewhere","rating":"6.5","general":false,"description":"Janice","professionKey":"ACTOR"},{"filmId":1219332,"nameRu":"Все мои сыновья","nameEn":"National Theatre Live: All My Sons","rating":null,"general":false,"description":"Кейт Келлер","professionKey":"ACTOR"},{"filmId":1263787,"nameRu":null,"nameEn":"HRC Americans for the Equality Act Awareness Campaign","rating":null,"general":false,"description":"","professionKey":"ACTOR"},{"filmId":1263787,"nameRu":null,"nameEn":"HRC Americans for the Equality Act Awareness Campaign","rating":null,"general":false,"description":"играет самого себя","professionKey":"HIMSELF"},{"filmId":1272097,"nameRu":"Время побеждать: Расцвет династии Лейкерс","nameEn":"Winning Time: The Rise of the Lakers Dynasty","rating":"8.6","general":false,"description":"Jessie Buss","professionKey":"ACTOR"},{"filmId":1366611,"nameRu":null,"nameEn":"Mrs. Doubtfire: Make-Up Tests","rating":null,"general":false,"description":"Self","professionKey":"ACTOR"},{"filmId":1411354,"nameRu":"Последние кинозвезды","nameEn":"The Last Movie Stars","rating":null,"general":false,"description":"играет саму себя","professionKey":"HERSELF"},{"filmId":4314781,"nameRu":null,"nameEn":"CBS News Sunday Morning","rating":null,"general":false,"description":"играет саму себя - гость","professionKey":"HERSELF"},{"filmId":4321994,"nameRu":null,"nameEn":"A Century of Women","rating":null,"general":false,"description":"","professionKey":"ACTOR"},{"filmId":4308224,"nameRu":"Я — Берт Рейнолдс","nameEn":"I Am Burt Reynolds","rating":null,"general":false,"description":"играет самого себя, хроника","professionKey":"HIMSELF"},{"filmId":4308224,"nameRu":"Я — Берт Рейнолдс","nameEn":"I Am Burt Reynolds","rating":null,"general":false,"description":"играет саму себя, хроника","professionKey":"HERSELF"},{"filmId":4473732,"nameRu":null,"nameEn":"Im Reich der Filme","rating":null,"general":false,"description":"играет саму себя, хроника","professionKey":"HERSELF"},{"filmId":724758,"nameRu":"85-я церемония вручения премии «Оскар»","nameEn":"The Oscars","rating":"7.1","general":false,"description":"играет саму себя - номинантка & Performer","professionKey":"HERSELF"},{"filmId":737979,"nameRu":"Церемония вручения премии Британской киноакадемии 2013","nameEn":"The EE British Academy Film Awards","rating":"6.3","general":false,"description":"играет саму себя - презентатор","professionKey":"HERSELF"},{"filmId":4542823,"nameRu":"Осторожно, спойлер!","nameEn":"Spoiler Alert","rating":"7.1","general":false,"description":"Marilyn","professionKey":"ACTOR"},{"filmId":4669798,"nameRu":"Hollywood Insider","nameEn":"","rating":null,"general":false,"description":"играет саму себя","professionKey":"HERSELF"},{"filmId":4540969,"nameRu":"Животрепещущие вопросы","nameEn":"Burning Questions","rating":null,"general":false,"description":"играет саму себя - гость","professionKey":"HERSELF"},{"filmId":94294,"nameRu":"Секрет успеха","nameEn":"A Woman of Independent Means","rating":null,"general":false,"description":"Bess Alcott Steed Garner","professionKey":"ACTOR"},{"filmId":94294,"nameRu":"Секрет успеха","nameEn":"A Woman of Independent Means","rating":null,"general":false,"description":"исполнительный продюсер","professionKey":"PRODUCER"},{"filmId":4909394,"nameRu":"80 для Брэди","nameEn":"80 for Brady","rating":"6.2","general":false,"description":"","professionKey":"ACTOR"},{"filmId":4909394,"nameRu":"80 для Брэди","nameEn":"80 for Brady","rating":"6.2","general":false,"description":"Betty","professionKey":"ACTOR"},{"filmId":5124573,"nameRu":null,"nameEn":"The Amazing Spider-Man: Deleted Scenes","rating":null,"general":false,"description":"Aunt May","professionKey":"ACTOR"}]}